kostal_plenticore_exporter/__init__.py
kostal_plenticore_exporter/__main__.py
kostal_plenticore_exporter/cli.py
kostal_plenticore_exporter/collector.py
kostal_plenticore_exporter-0.5.1.dist-info/entry_points.txt
kostal_plenticore_exporter-0.5.1.dist-info/COPYING.txt
kostal_plenticore_exporter-0.5.1.dist-info/WHEEL
kostal_plenticore_exporter-0.5.1.dist-info/METADATA
kostal_plenticore_exporter-0.5.1.dist-info/RECORD
