Metadata-Version: 2.1
Name: kostal_plenticore_exporter
Version: 0.5.1
Summary: A Prometheus exporter for the Kostal Plenticore series of inverters.
Home-page: https://codeberg.org/Marix/kostal-plenticore-exporter
License: AGPL-3.0-or-later
Author: Matthias Bach
Author-email: <marix@marix.org>
Requires-Python: >=3.6,<4
Classifier: Development Status :: 3 - Alpha
Classifier: Environment :: No Input/Output (Daemon)
Classifier: Intended Audience :: System Administrators
Classifier: License :: OSI Approved :: GNU Affero General Public License v3 or later (AGPLv3+)
Classifier: Operating System :: OS Independent
Classifier: Programming Language :: Python :: 3
Classifier: Topic :: System :: Monitoring
Requires-Dist: prometheus-client >= 0.7
Requires-Dist: kostalplenticore >= 0.3
Requires-Dist: click >= 7.0
Requires-Dist: pytest >=3.10; extra == "test"
Provides-Extra: test
